Workbook

Sheet Saisie
A1: GreenFlame — Suivi des Dépenses
A2: Saisissez vos dépenses ligne par ligne — colonnes Date, Catégorie et Montant obligatoires.
A3: Date | B3: Catégorie | C3: Description | D3: Montant (FCFA) | E3: Mode de paiement | F3: Notes
A4: 46174 | B4: Infrastructure & Hébergement | C4: Vercel Pro — juin 2026 | D4: 12000 | E4: Carte
A5: 46176 | B5: Légal & Juridique | C5: Honoraires conseiller | D5: 50000 | E5: MoMo | F5: Contrat mensuel
A6: 46178 | B6: Outils & Logiciels | C6: Supabase Pro — juin 2026 | D6: 8000 | E6: Carte

Sheet Budget
A1: GreenFlame — Budget Mensuel par Catégorie
A2: Période affichée : | B2: =MONTH(TODAY()) -> 6 | C2: =YEAR(TODAY()) -> 2026 | D2: ← Modifiez mois/année pour changer la période
A4: TOTAL | B4: =SUM(B6:B12) -> 175000 | C4: =SUM(C6:C12) -> 70000 | D4: =SUM(D6:D12) -> 105000 | E4: =IFERROR(C4/B4,0) -> 0.4
A5: Catégorie | B5: Budget mensuel (FCFA) | C5: Réalisé (FCFA) | D5: Écart (FCFA) | E5: % Consommé
A6: Infrastructure & Hébergement | B6: 25000 | C6: =SUMPRODUCT((MONTH(Saisie!$A$4:$A$200)=$B$2)*(YEAR(Saisie!$A$4:$A$200)=$C$2)*(Saisie!$B$4:$B$200=A6)*Saisie!$D$4:$D$200) -> 12000 | D6: =B6-C6 -> 13000 | E6: =IFERROR(C6/B6,0) -> 0.48
A7: Outils & Logiciels | B7: 15000 | C7: =SUMPRODUCT((MONTH(Saisie!$A$4:$A$200)=$B$2)*(YEAR(Saisie!$A$4:$A$200)=$C$2)*(Saisie!$B$4:$B$200=A7)*Saisie!$D$4:$D$200) -> 8000 | D7: =B7-C7 -> 7000 | E7: =IFERROR(C7/B7,0) -> 0.53333333
A8: Légal & Juridique | B8: 75000 | C8: =SUMPRODUCT((MONTH(Saisie!$A$4:$A$200)=$B$2)*(YEAR(Saisie!$A$4:$A$200)=$C$2)*(Saisie!$B$4:$B$200=A8)*Saisie!$D$4:$D$200) -> 50000 | D8: =B8-C8 -> 25000 | E8: =IFERROR(C8/B8,0) -> 0.66666667
A9: Marketing & Communication | B9: 30000 | C9: =SUMPRODUCT((MONTH(Saisie!$A$4:$A$200)=$B$2)*(YEAR(Saisie!$A$4:$A$200)=$C$2)*(Saisie!$B$4:$B$200=A9)*Saisie!$D$4:$D$200) -> 0 | D9: =B9-C9 -> 30000 | E9: =IFERROR(C9/B9,0) -> 0
A10: Terrain & Commercial | B10: 20000 | C10: =SUMPRODUCT((MONTH(Saisie!$A$4:$A$200)=$B$2)*(YEAR(Saisie!$A$4:$A$200)=$C$2)*(Saisie!$B$4:$B$200=A10)*Saisie!$D$4:$D$200) -> 0 | D10: =B10-C10 -> 20000 | E10: =IFERROR(C10/B10,0) -> 0
A11: Personnel & Associé | B11: 0 | C11: =SUMPRODUCT((MONTH(Saisie!$A$4:$A$200)=$B$2)*(YEAR(Saisie!$A$4:$A$200)=$C$2)*(Saisie!$B$4:$B$200=A11)*Saisie!$D$4:$D$200) -> 0 | D11: =B11-C11 -> 0 | E11: =IFERROR(C11/B11,0) -> 0
A12: Divers | B12: 10000 | C12: =SUMPRODUCT((MONTH(Saisie!$A$4:$A$200)=$B$2)*(YEAR(Saisie!$A$4:$A$200)=$C$2)*(Saisie!$B$4:$B$200=A12)*Saisie!$D$4:$D$200) -> 0 | D12: =B12-C12 -> 10000 | E12: =IFERROR(C12/B12,0) -> 0

Sheet Tableau de bord
A1: GreenFlame — Tableau de Bord Financier
A2: ="Période : mois "&Budget!B2&" / "&Budget!C2&" — Modifiez la période dans la feuille Budget" -> Période : mois 6 / 2026 — Modifiez la période dans la feuille Budget
A4: Budget mensuel total | C4: Total dépensé | E4: Solde restant | G4: Taux de consommation
A5: =Budget!B4 -> 175000 | C5: =Budget!C4 -> 70000 | E5: =Budget!D4 -> 105000 | G5: =IFERROR(Budget!C4/Budget!B4,0) -> 0.4
A8: DÉTAIL PAR CATÉGORIE — MOIS EN COURS
A9: Catégorie | B9: Budget | C9: Réalisé | D9: Écart | E9: % Consommé | F9: Jauge visuelle
A10: =Budget!A6 -> Infrastructure & Hébergement | B10: =Budget!B6 -> 25000 | C10: =Budget!C6 -> 12000 | D10: =Budget!D6 -> 13000 | E10: =Budget!E6 -> 0.48 | F10: =IFERROR(REPT("█",MIN(ROUND(Budget!E6*10,0),10))&REPT("░",10-MIN(ROUND(Budget!E6*10,0),10))&" "&TEXT(Budget!E6,"0%"),"-") -> █████░░░░░ 48%
A11: =Budget!A7 -> Outils & Logiciels | B11: =Budget!B7 -> 15000 | C11: =Budget!C7 -> 8000 | D11: =Budget!D7 -> 7000 | E11: =Budget!E7 -> 0.53333333 | F11: =IFERROR(REPT("█",MIN(ROUND(Budget!E7*10,0),10))&REPT("░",10-MIN(ROUND(Budget!E7*10,0),10))&" "&TEXT(Budget!E7,"0%"),"-") -> █████░░░░░ 53%
A12: =Budget!A8 -> Légal & Juridique | B12: =Budget!B8 -> 75000 | C12: =Budget!C8 -> 50000 | D12: =Budget!D8 -> 25000 | E12: =Budget!E8 -> 0.66666667 | F12: =IFERROR(REPT("█",MIN(ROUND(Budget!E8*10,0),10))&REPT("░",10-MIN(ROUND(Budget!E8*10,0),10))&" "&TEXT(Budget!E8,"0%"),"-") -> ███████░░░ 67%
A13: =Budget!A9 -> Marketing & Communication | B13: =Budget!B9 -> 30000 | C13: =Budget!C9 -> 0 | D13: =Budget!D9 -> 30000 | E13: =Budget!E9 -> 0 | F13: =IFERROR(REPT("█",MIN(ROUND(Budget!E9*10,0),10))&REPT("░",10-MIN(ROUND(Budget!E9*10,0),10))&" "&TEXT(Budget!E9,"0%"),"-") -> ░░░░░░░░░░ 0%
A14: =Budget!A10 -> Terrain & Commercial | B14: =Budget!B10 -> 20000 | C14: =Budget!C10 -> 0 | D14: =Budget!D10 -> 20000 | E14: =Budget!E10 -> 0 | F14: =IFERROR(REPT("█",MIN(ROUND(Budget!E10*10,0),10))&REPT("░",10-MIN(ROUND(Budget!E10*10,0),10))&" "&TEXT(Budget!E10,"0%"),"-") -> ░░░░░░░░░░ 0%
A15: =Budget!A11 -> Personnel & Associé | B15: =Budget!B11 -> 0 | C15: =Budget!C11 -> 0 | D15: =Budget!D11 -> 0 | E15: =Budget!E11 -> 0 | F15: =IFERROR(REPT("█",MIN(ROUND(Budget!E11*10,0),10))&REPT("░",10-MIN(ROUND(Budget!E11*10,0),10))&" "&TEXT(Budget!E11,"0%"),"-") -> ░░░░░░░░░░ 0%
A16: =Budget!A12 -> Divers | B16: =Budget!B12 -> 10000 | C16: =Budget!C12 -> 0 | D16: =Budget!D12 -> 10000 | E16: =Budget!E12 -> 0 | F16: =IFERROR(REPT("█",MIN(ROUND(Budget!E12*10,0),10))&REPT("░",10-MIN(ROUND(Budget!E12*10,0),10))&" "&TEXT(Budget!E12,"0%"),"-") -> ░░░░░░░░░░ 0%
A18: 5 DERNIÈRES DÉPENSES SAISIES
A19: Date | B19: Catégorie | C19: Description | D19: Montant (FCFA) | E19: Mode
A20: =IFERROR(INDEX(Saisie!A$4:A$200,MAX(COUNTA(Saisie!A$4:A$200)-0,1)),"") -> 46178 | B20: =IFERROR(INDEX(Saisie!B$4:B$200,MAX(COUNTA(Saisie!A$4:A$200)-0,1)),"") -> Outils & Logiciels | C20: =IFERROR(INDEX(Saisie!C$4:C$200,MAX(COUNTA(Saisie!A$4:A$200)-0,1)),"") -> Supabase Pro — juin 2026 | D20: =IFERROR(INDEX(Saisie!D$4:D$200,MAX(COUNTA(Saisie!A$4:A$200)-0,1)),"") -> 8000 | E20: =IFERROR(INDEX(Saisie!E$4:E$200,MAX(COUNTA(Saisie!A$4:A$200)-0,1)),"") -> Carte
A21: =IFERROR(INDEX(Saisie!A$4:A$200,MAX(COUNTA(Saisie!A$4:A$200)-1,1)),"") -> 46176 | B21: =IFERROR(INDEX(Saisie!B$4:B$200,MAX(COUNTA(Saisie!A$4:A$200)-1,1)),"") -> Légal & Juridique | C21: =IFERROR(INDEX(Saisie!C$4:C$200,MAX(COUNTA(Saisie!A$4:A$200)-1,1)),"") -> Honoraires conseiller | D21: =IFERROR(INDEX(Saisie!D$4:D$200,MAX(COUNTA(Saisie!A$4:A$200)-1,1)),"") -> 50000 | E21: =IFERROR(INDEX(Saisie!E$4:E$200,MAX(COUNTA(Saisie!A$4:A$200)-1,1)),"") -> MoMo
A22: =IFERROR(INDEX(Saisie!A$4:A$200,MAX(COUNTA(Saisie!A$4:A$200)-2,1)),"") -> 46174 | B22: =IFERROR(INDEX(Saisie!B$4:B$200,MAX(COUNTA(Saisie!A$4:A$200)-2,1)),"") -> Infrastructure & Hébergement | C22: =IFERROR(INDEX(Saisie!C$4:C$200,MAX(COUNTA(Saisie!A$4:A$200)-2,1)),"") -> Vercel Pro — juin 2026 | D22: =IFERROR(INDEX(Saisie!D$4:D$200,MAX(COUNTA(Saisie!A$4:A$200)-2,1)),"") -> 12000 | E22: =IFERROR(INDEX(Saisie!E$4:E$200,MAX(COUNTA(Saisie!A$4:A$200)-2,1)),"") -> Carte
A23: =IFERROR(INDEX(Saisie!A$4:A$200,MAX(COUNTA(Saisie!A$4:A$200)-3,1)),"") -> 46174 | B23: =IFERROR(INDEX(Saisie!B$4:B$200,MAX(COUNTA(Saisie!A$4:A$200)-3,1)),"") -> Infrastructure & Hébergement | C23: =IFERROR(INDEX(Saisie!C$4:C$200,MAX(COUNTA(Saisie!A$4:A$200)-3,1)),"") -> Vercel Pro — juin 2026 | D23: =IFERROR(INDEX(Saisie!D$4:D$200,MAX(COUNTA(Saisie!A$4:A$200)-3,1)),"") -> 12000 | E23: =IFERROR(INDEX(Saisie!E$4:E$200,MAX(COUNTA(Saisie!A$4:A$200)-3,1)),"") -> Carte
A24: =IFERROR(INDEX(Saisie!A$4:A$200,MAX(COUNTA(Saisie!A$4:A$200)-4,1)),"") -> 46174 | B24: =IFERROR(INDEX(Saisie!B$4:B$200,MAX(COUNTA(Saisie!A$4:A$200)-4,1)),"") -> Infrastructure & Hébergement | C24: =IFERROR(INDEX(Saisie!C$4:C$200,MAX(COUNTA(Saisie!A$4:A$200)-4,1)),"") -> Vercel Pro — juin 2026 | D24: =IFERROR(INDEX(Saisie!D$4:D$200,MAX(COUNTA(Saisie!A$4:A$200)-4,1)),"") -> 12000 | E24: =IFERROR(INDEX(Saisie!E$4:E$200,MAX(COUNTA(Saisie!A$4:A$200)-4,1)),"") -> Carte
